pynotedb/__init__.py
pynotedb/utils.py
pynotedb-0.2.3.dist-info/LICENSE
pynotedb-0.2.3.dist-info/METADATA
pynotedb-0.2.3.dist-info/WHEEL
pynotedb-0.2.3.dist-info/entry_points.txt
pynotedb-0.2.3.dist-info/top_level.txt
pynotedb-0.2.3.dist-info/RECORD
