Metadata-Version: 2.1
Name: pynotedb
Version: 0.2.3
Summary: A Gerrit notedb helper library
Home-page: UNKNOWN
License: UNKNOWN
Platform: UNKNOWN
